_polar_lib.abi3.so
oso_yurts-0.27.3.dist-info/top_level.txt
oso_yurts-0.27.3.dist-info/WHEEL
oso_yurts-0.27.3.dist-info/METADATA
oso_yurts-0.27.3.dist-info/RECORD
polar/variable.py
polar/__init__.py
polar/predicate.py
polar/host.py
polar/partial.py
polar/py.typed
polar/ffi.py
polar/errors.py
polar/exceptions.py
polar/query.py
polar/build.py
polar/__main__.py
polar/polar.py
polar/data_filtering.py
polar/expression.py
polar/data/__init__.py
polar/data/filter.py
polar/data/adapter/__init__.py
polar/data/adapter/adapter.py
polar/data/adapter/sqlalchemy_adapter.py
oso/__init__.py
oso/py.typed
oso/oso.py
oso/exceptions.py
oso/__main__.py
